[
    {
        "title": "초코를 잠시 돌봐주세요!",
        "content": "군자역 5번출구 쪽에 초코와 함께 살고있는 2년차 견주에요~ 아직 어린 강아지라 손이 많이 갈 수도 있어요.",
        "user": {
            "name": "홍길동",
            "recommendationCount": 12,
            "careCount": 3,
            "entrustCount": 5,
            "gender": "male"
        },
        "dog": {
            "name": "초코",
            "gender": "female",
            "size": "소형",
            "neutered": true,
            "breed": "푸들",
            "age": 2,
            "img": "https://images.unsplash.com/photo-1517849845537-4d257902454a"
        },
        "startDate": "2024-11-18 11:30",
        "endDate": "2024-11-18 13:30",
        "wantPrice": 15000,
        "wantPriceType": "hour",
        "createdAt": "2024-11-17T01:22:00Z"
    },
    {
        "title": "초코를 잠시 돌봐주세요!",
        "content": "군자역 5번출구 쪽에 초코와 함께 살고있는 2년차 견주에요~ 아직 어린 강아지라 손이 많이 갈 수도 있어요.",
        "user": {
            "name": "홍길동",
            "recommendationCount": 12,
            "careCount": 3,
            "entrustCount": 5,
            "gender": "male"
        },
        "dog": {
            "name": "초코",
            "gender": "female",
            "size": "소형",
            "neutered": true,
            "breed": "푸들",
            "age": 2,
            "img": "https://images.unsplash.com/photo-1517849845537-4d257902454a"
        },
        "startDate": "2024-11-18 11:30",
        "endDate": "2024-11-18 13:30",
        "wantPrice": 15000,
        "wantPriceType": "hour",
        "createdAt": "2024-11-17T01:22:00Z"
    },
    {
        "title": "초코를 잠시 돌봐주세요!",
        "content": "군자역 5번출구 쪽에 초코와 함께 살고있는 2년차 견주에요~ 아직 어린 강아지라 손이 많이 갈 수도 있어요.",
        "user": {
            "name": "홍길동",
            "recommendationCount": 12,
            "careCount": 3,
            "entrustCount": 5,
            "gender": "male"
        },
        "dog": {
            "name": "초코",
            "gender": "female",
            "size": "소형",
            "neutered": true,
            "breed": "푸들",
            "age": 2,
            "img": "https://images.unsplash.com/photo-1517849845537-4d257902454a"
        },
        "startDate": "2024-11-18 11:30",
        "endDate": "2024-11-18 13:30",
        "wantPrice": 15000,
        "wantPriceType": "hour",
        "createdAt": "2024-11-17T01:22:00Z"
    },
    {
        "title": "초코를 잠시 돌봐주세요!",
        "content": "군자역 5번출구 쪽에 초코와 함께 살고있는 2년차 견주에요~ 아직 어린 강아지라 손이 많이 갈 수도 있어요.",
        "user": {
            "name": "홍길동",
            "recommendationCount": 12,
            "careCount": 3,
            "entrustCount": 5,
            "gender": "male"
        },
        "dog": {
            "name": "초코",
            "gender": "female",
            "size": "소형",
            "neutered": true,
            "breed": "푸들",
            "age": 2,
            "img": "https://images.unsplash.com/photo-1517849845537-4d257902454a"
        },
        "startDate": "2024-11-18 11:30",
        "endDate": "2024-11-18 13:30",
        "wantPrice": 15000,
        "wantPriceType": "hour",
        "createdAt": "2024-11-17T01:22:00Z"
    },
    {
        "title": "초코를 잠시 돌봐주세요!",
        "content": "군자역 5번출구 쪽에 초코와 함께 살고있는 2년차 견주에요~ 아직 어린 강아지라 손이 많이 갈 수도 있어요.",
        "user": {
            "name": "홍길동",
            "recommendationCount": 12,
            "careCount": 3,
            "entrustCount": 5,
            "gender": "male"
        },
        "dog": {
            "name": "초코",
            "gender": "female",
            "size": "소형",
            "neutered": true,
            "breed": "푸들",
            "age": 2,
            "img": "https://images.unsplash.com/photo-1517849845537-4d257902454a"
        },
        "startDate": "2024-11-18 11:30",
        "endDate": "2024-11-18 13:30",
        "wantPrice": 15000,
        "wantPriceType": "hour",
        "createdAt": "2024-11-17T01:22:00Z"
    }
]
